examples/basic_usage.py
examples/hierarchical_config.py
examples/provenance_tracking.py
herrkunft/__init__.py
herrkunft/exceptions.py
herrkunft/py.typed
herrkunft/version.py
herrkunft/config/__init__.py
herrkunft/config/settings.py
herrkunft/core/__init__.py
herrkunft/core/decorators.py
herrkunft/core/hierarchy.py
herrkunft/core/provenance.py
herrkunft/types/__init__.py
herrkunft/types/base.py
herrkunft/types/factory.py
herrkunft/types/mappings.py
herrkunft/types/wrappers.py
herrkunft/utils/__init__.py
herrkunft/utils/cleaning.py
herrkunft/utils/serialization.py
herrkunft/utils/validation.py
herrkunft/yaml/__init__.py
herrkunft/yaml/constructors.py
herrkunft/yaml/dumper.py
herrkunft/yaml/loader.py
herrkunft/yaml/utils.py
tests/__init__.py
tests/test_core_provenance.py
tests/test_hierarchy.py
tests/test_integration.py
tests/test_mappings.py
tests/test_type_factory.py
tests/test_type_wrappers.py
tests/test_yaml_dumper.py
tests/test_yaml_loader.py
herrkunft-0.1.0.dist-info/METADATA
herrkunft-0.1.0.dist-info/WHEEL
herrkunft-0.1.0.dist-info/top_level.txt
herrkunft-0.1.0.dist-info/RECORD
