Metadata-Version: 2.4
Name: herrkunft
Version: 0.1.0
Summary: Track configuration value origins and modification history through YAML parsing
Author-email: Paul Gierz <paul.gierz@awi.de>, Miguel Andrés-Martínez <miguel.andres-martinez@awi.de>
Maintainer-email: Paul Gierz <paul.gierz@awi.de>, Miguel Andrés-Martínez <miguel.andres-martinez@awi.de>
License: MIT
Project-URL: Homepage, https://github.com/pgierz/herrkunft
Project-URL: Documentation, https://herrkunft.readthedocs.io
Project-URL: Repository, https://github.com/pgierz/herrkunft
Project-URL: Issues, https://github.com/pgierz/herrkunft/issues
Keywords: provenance,configuration,yaml,tracking,metadata,scientific-computing
Classifier: Development Status :: 3 - Alpha
Classifier: Intended Audience :: Developers
Classifier: Intended Audience :: Science/Research
Classifier: License :: OSI Approved :: MIT License
Classifier: Programming Language :: Python :: 3
Classifier: Programming Language :: Python :: 3.9
Classifier: Programming Language :: Python :: 3.10
Classifier: Programming Language :: Python :: 3.11
Classifier: Programming Language :: Python :: 3.12
Classifier: Topic :: Software Development :: Libraries :: Python Modules
Classifier: Topic :: Scientific/Engineering
Classifier: Typing :: Typed
Requires-Python: >=3.9
Requires-Dist: pydantic<3.0.0,>=2.0.0
Requires-Dist: pydantic-settings<3.0.0,>=2.0.0
Requires-Dist: ruamel.yaml<1.0.0,>=0.17.32
Requires-Dist: loguru<1.0.0,>=0.7.0
Requires-Dist: typing-extensions>=4.0.0; python_version < "3.11"
Provides-Extra: dev
Requires-Dist: pytest>=7.4.0; extra == "dev"
Requires-Dist: pytest-cov>=4.1.0; extra == "dev"
Requires-Dist: pytest-xdist>=3.3.0; extra == "dev"
Requires-Dist: mypy>=1.5.0; extra == "dev"
Requires-Dist: black>=23.7.0; extra == "dev"
Requires-Dist: ruff>=0.0.285; extra == "dev"
Requires-Dist: pre-commit>=3.3.0; extra == "dev"
Provides-Extra: docs
Requires-Dist: sphinx>=7.0.0; extra == "docs"
Requires-Dist: sphinx-rtd-theme>=1.3.0; extra == "docs"
Requires-Dist: myst-parser>=2.0.0; extra == "docs"
Provides-Extra: all
Requires-Dist: herrkunft[dev,docs]; extra == "all"
